src/__init__.py
src/main.py
src/lib/cloning.py
src/lib/commit_analysis.py
src/lib/primary_language.py
src/lib/resources/file_extensions.json
repo_lifecycles-0.0.4.dist-info/METADATA
repo_lifecycles-0.0.4.dist-info/WHEEL
repo_lifecycles-0.0.4.dist-info/licenses/LICENSE
repo_lifecycles-0.0.4.dist-info/RECORD
