Metadata-Version: 2.3
Name: repo-lifecycles
Version: 0.0.4
Summary: Lightweight longitudinal repository data collector.
Project-URL: Homepage, https://github.com/mjgaughan/repo-lifecycles
Project-URL: Issues, https://github.com/mjgaughan/repo-lifecycles/issues
Author-email: Matt Gaughan <mgaughan@proton.me>
Maintainer-email: Matt Gaughan <mgaughan@proton.me>
Classifier: Programming Language :: Python
Requires-Python: >=3.8
Requires-Dist: gitpython
Requires-Dist: pandas
